{"played_against": {"56ab442f": {"runs": 9, "balls": 9, "wickets": 1}, "acee4cc4": {"runs": 2, "balls": 3, "wickets": 0}, "957532de": {"runs": 1, "balls": 1, "wickets": 0}, "edb3d4f8": {"runs": 1, "balls": 5, "wickets": 1}, "40792cff": {"runs": 7, "balls": 4, "wickets": 0}, "7c7d63a2": {"runs": 7, "balls": 4, "wickets": 1}, "350bb1b1": {"runs": 0, "balls": 1, "wickets": 1}, "dcf81436": {"runs": 15, "balls": 6, "wickets": 1}, "d3611425": {"runs": 5, "balls": 3, "wickets": 0}, "4312e8f9": {"runs": 0, "balls": 2, "wickets": 1}, "4c7543cf": {"runs": 1, "balls": 1, "wickets": 0}, "76cc7070": {"runs": 2, "balls": 2, "wickets": 0}, "7f048519": {"runs": 11, "balls": 10, "wickets": 0}, "8d92a2c3": {"runs": 11, "balls": 8, "wickets": 1}, "e087956b": {"runs": 26, "balls": 18, "wickets": 1}, "d5ae21a2": {"runs": 0, "balls": 2, "wickets": 0}, "f6c2659d": {"runs": 0, "balls": 1, "wickets": 1}, "cc23e91e": {"runs": 3, "balls": 8, "wickets": 0}, "0f721006": {"runs": 1, "balls": 1, "wickets": 0}, "7a80ddf2": {"runs": 0, "balls": 3, "wickets": 0}, "d8b2f218": {"runs": 0, "balls": 1, "wickets": 1}, "254c7802": {"runs": 2, "balls": 2, "wickets": 0}, "4a15018a": {"runs": 2, "balls": 4, "wickets": 0}, "27e71d47": {"runs": 1, "balls": 1, "wickets": 0}, "1d8388eb": {"runs": 3, "balls": 4, "wickets": 1}, "69be866a": {"runs": 1, "balls": 2, "wickets": 0}, "85e0cf10": {"runs": 5, "balls": 2, "wickets": 0}, "41eb4a4f": {"runs": 1, "balls": 1, "wickets": 0}, "f6cb1703": {"runs": 3, "balls": 4, "wickets": 0}, "a12e1d51": {"runs": 10, "balls": 6, "wickets": 0}, "462411b3": {"runs": 17, "balls": 9, "wickets": 0}, "dbe50b21": {"runs": 11, "balls": 3, "wickets": 0}, "c7a995d3": {"runs": 0, "balls": 1, "wickets": 0}, "f19ccfad": {"runs": 1, "balls": 6, "wickets": 0}, "e2db2409": {"runs": 4, "balls": 6, "wickets": 0}, "2e099662": {"runs": 3, "balls": 7, "wickets": 1}, "1b7c4d69": {"runs": 2, "balls": 3, "wickets": 0}, "75224f22": {"runs": 6, "balls": 3, "wickets": 0}, "a1d053dd": {"runs": 11, "balls": 3, "wickets": 0}, "4751caa3": {"runs": 14, "balls": 5, "wickets": 0}, "dfc4d8b5": {"runs": 2, "balls": 4, "wickets": 0}, "ded9240e": {"runs": 77, "balls": 79, "wickets": 1}, "3fb19989": {"runs": 32, "balls": 42, "wickets": 1}, "e4a0deae": {"runs": 4, "balls": 8, "wickets": 0}, "641ac5ff": {"runs": 7, "balls": 4, "wickets": 0}, "94238673": {"runs": 12, "balls": 13, "wickets": 2}, "13c35c9e": {"runs": 15, "balls": 11, "wickets": 1}, "9219eff0": {"runs": 13, "balls": 7, "wickets": 0}, "94d7f855": {"runs": 0, "balls": 1, "wickets": 1}, "ac5ae4af": {"runs": 1, "balls": 1, "wickets": 0}, "2ed569a0": {"runs": 8, "balls": 10, "wickets": 0}, "a757b0d8": {"runs": 2, "balls": 4, "wickets": 0}, "5b8c830e": {"runs": 2, "balls": 4, "wickets": 0}, "1a2676c5": {"runs": 10, "balls": 4, "wickets": 0}, "03806cf8": {"runs": 12, "balls": 20, "wickets": 2}, "96a6a7ad": {"runs": 11, "balls": 51, "wickets": 0}, "fa433be6": {"runs": 0, "balls": 6, "wickets": 0}, "5574750c": {"runs": 6, "balls": 4, "wickets": 1}, "8db7f47f": {"runs": 13, "balls": 7, "wickets": 0}, "0a8fce53": {"runs": 8, "balls": 9, "wickets": 2}, "d12143bf": {"runs": 15, "balls": 16, "wickets": 1}, "e9987a94": {"runs": 14, "balls": 14, "wickets": 0}, "0f3ee070": {"runs": 26, "balls": 25, "wickets": 0}, "4c5d73db": {"runs": 46, "balls": 32, "wickets": 0}, "bb351c23": {"runs": 18, "balls": 25, "wickets": 0}, "a343262c": {"runs": 1, "balls": 6, "wickets": 1}, "9d430b40": {"runs": 4, "balls": 5, "wickets": 0}, "e86754b2": {"runs": 0, "balls": 1, "wickets": 1}, "a818c1be": {"runs": 7, "balls": 5, "wickets": 1}, "e62dd25d": {"runs": 33, "balls": 48, "wickets": 4}, "81c36ee9": {"runs": 38, "balls": 44, "wickets": 1}, "a8e56914": {"runs": 5, "balls": 12, "wickets": 1}, "f834dcfc": {"runs": 39, "balls": 34, "wickets": 2}, "0b60eb09": {"runs": 20, "balls": 20, "wickets": 1}, "ab6b1c45": {"runs": 21, "balls": 18, "wickets": 0}, "a03bba42": {"runs": 28, "balls": 29, "wickets": 0}, "8361e524": {"runs": 6, "balls": 3, "wickets": 0}, "b52ffbbd": {"runs": 2, "balls": 6, "wickets": 0}, "4d7f517e": {"runs": 3, "balls": 7, "wickets": 0}, "b0946605": {"runs": 7, "balls": 9, "wickets": 2}, "871e9faf": {"runs": 1, "balls": 2, "wickets": 1}, "caf69bf7": {"runs": 7, "balls": 3, "wickets": 0}, "2f9d0389": {"runs": 7, "balls": 6, "wickets": 0}, "5f547c8b": {"runs": 3, "balls": 6, "wickets": 0}, "cc1e8c68": {"runs": 14, "balls": 5, "wickets": 0}, "a97c8ec2": {"runs": 7, "balls": 2, "wickets": 0}, "2f49c897": {"runs": 12, "balls": 8, "wickets": 1}, "f986ca1a": {"runs": 19, "balls": 11, "wickets": 1}, "495d42a5": {"runs": 2, "balls": 2, "wickets": 0}, "57ee1fde": {"runs": 2, "balls": 5, "wickets": 0}, "a24be938": {"runs": 2, "balls": 2, "wickets": 0}, "85ec8e33": {"runs": 1, "balls": 5, "wickets": 0}, "c33d8116": {"runs": 1, "balls": 2, "wickets": 1}, "765a4731": {"runs": 2, "balls": 2, "wickets": 0}, "87e562a9": {"runs": 9, "balls": 5, "wickets": 1}, "f24c6701": {"runs": 10, "balls": 7, "wickets": 0}, "30df8c66": {"runs": 1, "balls": 1, "wickets": 0}, "244048f6": {"runs": 3, "balls": 4, "wickets": 1}, "be24ead0": {"runs": 2, "balls": 3, "wickets": 1}, "3987e390": {"runs": 2, "balls": 10, "wickets": 0}, "894b2d25": {"runs": 2, "balls": 16, "wickets": 1}, "c5aef772": {"runs": 19, "balls": 15, "wickets": 0}, "6e3f5a5c": {"runs": 5, "balls": 4, "wickets": 0}, "e7e86505": {"runs": 4, "balls": 2, "wickets": 1}, "3a60e0b5": {"runs": 1, "balls": 3, "wickets": 0}, "cb5100f1": {"runs": 4, "balls": 8, "wickets": 0}, "7dc35884": {"runs": 2, "balls": 12, "wickets": 1}, "37654b75": {"runs": 1, "balls": 4, "wickets": 0}, "c58b0108": {"runs": 2, "balls": 2, "wickets": 0}, "ef18b66e": {"runs": 1, "balls": 1, "wickets": 0}, "48ad3373": {"runs": 15, "balls": 10, "wickets": 1}, "dadbdb68": {"runs": 5, "balls": 2, "wickets": 0}, "e94915e6": {"runs": 18, "balls": 5, "wickets": 0}, "119678fd": {"runs": 12, "balls": 6, "wickets": 0}, "0a67aec0": {"runs": 16, "balls": 5, "wickets": 0}, "e38bce7a": {"runs": 14, "balls": 4, "wickets": 0}, "ce794613": {"runs": 5, "balls": 3, "wickets": 1}, "2e81a32d": {"runs": 13, "balls": 7, "wickets": 0}, "81c08fa3": {"runs": 0, "balls": 1, "wickets": 1}, "0c9652b0": {"runs": 4, "balls": 5, "wickets": 1}, "98ae73b1": {"runs": 2, "balls": 2, "wickets": 0}, "64775749": {"runs": 1, "balls": 1, "wickets": 0}, "8dc152d1": {"runs": 6, "balls": 3, "wickets": 0}, "8cf9814c": {"runs": 0, "balls": 4, "wickets": 1}, "a9fd84fb": {"runs": 2, "balls": 2, "wickets": 0}, "df064e1a": {"runs": 1, "balls": 2, "wickets": 0}, "c0c411cb": {"runs": 2, "balls": 3, "wickets": 0}, "4b31f3a3": {"runs": 0, "balls": 1, "wickets": 1}, "d167edd3": {"runs": 10, "balls": 23, "wickets": 0}, "eaa76d3c": {"runs": 4, "balls": 14, "wickets": 1}, "97bdec3d": {"runs": 4, "balls": 11, "wickets": 0}, "78bb68d4": {"runs": 0, "balls": 1, "wickets": 1}, "45a7e761": {"runs": 3, "balls": 2, "wickets": 0}, "9c9af282": {"runs": 0, "balls": 1, "wickets": 1}, "9dad0f2e": {"runs": 6, "balls": 7, "wickets": 0}, "3204c99f": {"runs": 16, "balls": 20, "wickets": 0}, "465aa633": {"runs": 3, "balls": 4, "wickets": 0}, "759ac88f": {"runs": 2, "balls": 3, "wickets": 0}, "7210d461": {"runs": 1, "balls": 2, "wickets": 0}}, "fifties": 1, "thirties": 7, "centuries": 0, "maidens": 47.0, "hattricks": 22, "club_ODI_previous3_runs": [], "club_ODI_previous3_wickets": [], "club_ODI_previous3_balls played": [], "club_ODI_previous3_overs": [], "club_ODI_previous3_runs gave": [], "club_ODI_lifetime_runs": 0.0, "club_ODI_lifetime_wickets": 0.0, "club_ODI_lifetime_balls played": 0.0, "club_ODI_lifetime_overs": 0.0, "club_ODI_lifetime_runs gave": 0.0, "club_Test_previous3_runs": [], "club_Test_previous3_wickets": [], "club_Test_previous3_balls played": [], "club_Test_previous3_overs": [], "club_Test_previous3_runs gave": [], "club_Test_lifetime_runs": 0.0, "club_Test_lifetime_wickets": 0.0, "club_Test_lifetime_balls played": 0.0, "club_Test_lifetime_overs": 0.0, "club_Test_lifetime_runs gave": 0.0, "club_T20_previous3_runs": [3.0, 0.0, 1.0], "club_T20_previous3_wickets": [0.0, 0.0, 2.0], "club_T20_previous3_balls played": [4.0, 0.0, 2.0], "club_T20_previous3_overs": [4.0, 4.0, 4.0], "club_T20_previous3_runs gave": [26.0, 32.0, 62.0], "club_T20_lifetime_runs": 351.0, "club_T20_lifetime_wickets": 122.0, "club_T20_lifetime_balls played": 281.0, "club_T20_lifetime_overs": 412.0, "club_T20_lifetime_runs gave": 3709.0, "international_ODI_previous3_runs": [0.0, 0.0, 0.0], "international_ODI_previous3_wickets": [0.0, 0.0, 1.0], "international_ODI_previous3_balls played": [0.0, 0.0, 0.0], "international_ODI_previous3_overs": [4.0, 2.0, 9.0], "international_ODI_previous3_runs gave": [35.0, 12.0, 59.0], "international_ODI_lifetime_runs": 329.0, "international_ODI_lifetime_wickets": 57.0, "international_ODI_lifetime_balls played": 310.0, "international_ODI_lifetime_overs": 317.1666666666667, "international_ODI_lifetime_runs gave": 2010.0, "international_Test_previous3_runs": [51.0, 0.0, 26.0], "international_Test_previous3_wickets": [2.0, 1.0, 1.0], "international_Test_previous3_balls played": [110.0, 0.0, 41.0], "international_Test_previous3_overs": [31.0, 7.0, 19.0], "international_Test_previous3_runs gave": [108.0, 15.0, 102.0], "international_Test_lifetime_runs": 331.0, "international_Test_lifetime_wickets": 25.0, "international_Test_lifetime_balls played": 512.0, "international_Test_lifetime_overs": 241.66666666666669, "international_Test_lifetime_runs gave": 895.0, "international_T20_previous3_runs": [0.0, 0.0, 0.0], "international_T20_previous3_wickets": [3.0, 0.0, 2.0], "international_T20_previous3_balls played": [0.0, 3.0, 0.0], "international_T20_previous3_overs": [4.0, 1.5, 4.0], "international_T20_previous3_runs gave": [45.0, 17.0, 33.0], "international_T20_lifetime_runs": 69.0, "international_T20_lifetime_wickets": 32.0, "international_T20_lifetime_balls played": 38.0, "international_T20_lifetime_overs": 81.0, "international_T20_lifetime_runs gave": 756.0}