{"played_against": {"eb2d5fe7": {"runs": 10, "balls": 10, "wickets": 0}, "64d43928": {"runs": 2, "balls": 3, "wickets": 0}, "a8e3170f": {"runs": 11, "balls": 13, "wickets": 0}, "0dc00542": {"runs": 19, "balls": 17, "wickets": 1}, "9cb8d7a6": {"runs": 4, "balls": 4, "wickets": 0}, "64c34cd0": {"runs": 4, "balls": 8, "wickets": 2}, "3540beff": {"runs": 14, "balls": 23, "wickets": 0}, "3fb19989": {"runs": 132, "balls": 208, "wickets": 4}, "03806cf8": {"runs": 72, "balls": 104, "wickets": 1}, "96a6a7ad": {"runs": 126, "balls": 246, "wickets": 3}, "3d8feaf8": {"runs": 33, "balls": 60, "wickets": 1}, "70c4f525": {"runs": 56, "balls": 100, "wickets": 0}, "30a45b23": {"runs": 15, "balls": 12, "wickets": 0}, "808f425a": {"runs": 35, "balls": 50, "wickets": 3}, "14f96089": {"runs": 33, "balls": 49, "wickets": 1}, "012829ff": {"runs": 43, "balls": 41, "wickets": 1}, "d167edd3": {"runs": 33, "balls": 31, "wickets": 0}, "b681e71e": {"runs": 15, "balls": 12, "wickets": 0}, "32198ae0": {"runs": 9, "balls": 8, "wickets": 0}, "9f0270e0": {"runs": 69, "balls": 133, "wickets": 2}, "28496266": {"runs": 95, "balls": 127, "wickets": 2}, "49691d7a": {"runs": 32, "balls": 67, "wickets": 0}, "dbfb8218": {"runs": 58, "balls": 136, "wickets": 0}, "31fbf891": {"runs": 13, "balls": 25, "wickets": 0}, "afe57f7a": {"runs": 39, "balls": 62, "wickets": 0}, "ec4dada1": {"runs": 13, "balls": 20, "wickets": 0}, "3b417422": {"runs": 24, "balls": 29, "wickets": 0}, "f32dbc84": {"runs": 13, "balls": 7, "wickets": 0}, "26d041c4": {"runs": 34, "balls": 40, "wickets": 1}, "d9609443": {"runs": 64, "balls": 107, "wickets": 2}, "0f721006": {"runs": 71, "balls": 118, "wickets": 2}, "e342e5fb": {"runs": 12, "balls": 13, "wickets": 1}, "4a745f65": {"runs": 13, "balls": 14, "wickets": 0}, "7d5af2ea": {"runs": 35, "balls": 46, "wickets": 1}, "37137c8b": {"runs": 0, "balls": 1, "wickets": 0}, "e62dd25d": {"runs": 113, "balls": 192, "wickets": 2}, "0b60eb09": {"runs": 161, "balls": 260, "wickets": 2}, "cfe70281": {"runs": 21, "balls": 43, "wickets": 2}, "a9da7784": {"runs": 18, "balls": 34, "wickets": 0}, "2e8994e7": {"runs": 40, "balls": 37, "wickets": 2}, "a8e56914": {"runs": 42, "balls": 57, "wickets": 1}, "3a60e0b5": {"runs": 28, "balls": 42, "wickets": 1}, "f834dcfc": {"runs": 54, "balls": 62, "wickets": 2}, "ab6b1c45": {"runs": 60, "balls": 61, "wickets": 3}, "acee4cc4": {"runs": 118, "balls": 142, "wickets": 3}, "7f8ecc51": {"runs": 1, "balls": 2, "wickets": 0}, "42172c3c": {"runs": 3, "balls": 3, "wickets": 0}, "fb66ce1f": {"runs": 15, "balls": 26, "wickets": 1}, "a3a078ba": {"runs": 4, "balls": 8, "wickets": 0}, "7dc35884": {"runs": 105, "balls": 177, "wickets": 4}, "0a8fce53": {"runs": 89, "balls": 110, "wickets": 2}, "c58b0108": {"runs": 159, "balls": 288, "wickets": 3}, "9d1d34bd": {"runs": 185, "balls": 350, "wickets": 4}, "e174dadd": {"runs": 3, "balls": 6, "wickets": 0}, "086f5984": {"runs": 0, "balls": 3, "wickets": 1}, "fe93fd9d": {"runs": 79, "balls": 191, "wickets": 4}, "8cf9814c": {"runs": 38, "balls": 87, "wickets": 1}, "5bb1a1c4": {"runs": 12, "balls": 16, "wickets": 0}, "495d42a5": {"runs": 60, "balls": 78, "wickets": 1}, "4b57e452": {"runs": 1, "balls": 2, "wickets": 0}, "ba607b88": {"runs": 0, "balls": 3, "wickets": 0}, "0f348f58": {"runs": 53, "balls": 72, "wickets": 0}, "8919756f": {"runs": 1, "balls": 1, "wickets": 0}, "de0a3209": {"runs": 8, "balls": 12, "wickets": 0}, "bf1d7d3e": {"runs": 4, "balls": 5, "wickets": 0}, "888e32bf": {"runs": 20, "balls": 18, "wickets": 0}, "78eb4223": {"runs": 33, "balls": 69, "wickets": 1}, "8fd1a8f5": {"runs": 29, "balls": 57, "wickets": 0}, "a03bba42": {"runs": 83, "balls": 96, "wickets": 2}, "33085ffb": {"runs": 7, "balls": 9, "wickets": 0}, "6a26221c": {"runs": 23, "balls": 25, "wickets": 1}, "c96f6ac5": {"runs": 34, "balls": 63, "wickets": 2}, "1cb14aa4": {"runs": 16, "balls": 10, "wickets": 1}, "e186f49c": {"runs": 0, "balls": 3, "wickets": 0}, "4c5d73db": {"runs": 24, "balls": 39, "wickets": 1}, "4a461c24": {"runs": 13, "balls": 17, "wickets": 0}, "bb351c23": {"runs": 99, "balls": 117, "wickets": 1}, "3f659464": {"runs": 23, "balls": 25, "wickets": 0}, "249d60c9": {"runs": 66, "balls": 110, "wickets": 2}, "e087956b": {"runs": 14, "balls": 23, "wickets": 1}, "e86754b2": {"runs": 38, "balls": 44, "wickets": 2}, "8d92a2c3": {"runs": 42, "balls": 49, "wickets": 1}, "bdadf7da": {"runs": 2, "balls": 3, "wickets": 0}, "ffe699c0": {"runs": 9, "balls": 5, "wickets": 0}, "d12143bf": {"runs": 12, "balls": 32, "wickets": 0}, "e94915e6": {"runs": 19, "balls": 30, "wickets": 1}, "3987e390": {"runs": 43, "balls": 137, "wickets": 1}, "a343262c": {"runs": 19, "balls": 27, "wickets": 0}, "eba6a852": {"runs": 5, "balls": 11, "wickets": 0}, "a818c1be": {"runs": 59, "balls": 89, "wickets": 2}, "13c35c9e": {"runs": 99, "balls": 162, "wickets": 3}, "e84ac20c": {"runs": 67, "balls": 88, "wickets": 0}, "2f9d0389": {"runs": 19, "balls": 25, "wickets": 1}, "641ac5ff": {"runs": 17, "balls": 16, "wickets": 0}, "fef92afc": {"runs": 2, "balls": 2, "wickets": 0}, "1ee08e9a": {"runs": 17, "balls": 53, "wickets": 3}, "ded9240e": {"runs": 33, "balls": 60, "wickets": 1}, "acdc62f5": {"runs": 28, "balls": 37, "wickets": 1}, "11614d87": {"runs": 22, "balls": 30, "wickets": 1}, "f892fcf9": {"runs": 15, "balls": 15, "wickets": 0}, "f43dd8c2": {"runs": 3, "balls": 4, "wickets": 0}, "1252f71a": {"runs": 10, "balls": 16, "wickets": 1}, "4933f499": {"runs": 3, "balls": 4, "wickets": 0}, "dfc4d8b5": {"runs": 5, "balls": 5, "wickets": 0}, "5574750c": {"runs": 2, "balls": 5, "wickets": 1}, "a1d053dd": {"runs": 32, "balls": 33, "wickets": 3}, "8d2c70ad": {"runs": 65, "balls": 62, "wickets": 0}, "462411b3": {"runs": 22, "balls": 32, "wickets": 0}, "dbe50b21": {"runs": 10, "balls": 14, "wickets": 0}, "2e81a32d": {"runs": 20, "balls": 22, "wickets": 0}, "1a8eebbe": {"runs": 10, "balls": 6, "wickets": 1}, "fbd4f01f": {"runs": 53, "balls": 116, "wickets": 2}, "94d7f855": {"runs": 11, "balls": 21, "wickets": 0}, "a089f93f": {"runs": 13, "balls": 29, "wickets": 0}, "45a7e761": {"runs": 75, "balls": 130, "wickets": 4}, "f0e722e0": {"runs": 24, "balls": 27, "wickets": 0}, "9c9af282": {"runs": 114, "balls": 175, "wickets": 2}, "7cd0a092": {"runs": 1, "balls": 3, "wickets": 0}, "50250426": {"runs": 2, "balls": 6, "wickets": 0}, "f2800ef3": {"runs": 84, "balls": 123, "wickets": 2}, "21d4e29b": {"runs": 21, "balls": 14, "wickets": 1}, "1abb78f8": {"runs": 1, "balls": 2, "wickets": 1}, "f19ccfad": {"runs": 13, "balls": 10, "wickets": 0}, "57ee1fde": {"runs": 43, "balls": 40, "wickets": 2}, "59792462": {"runs": 20, "balls": 42, "wickets": 0}, "1bd16445": {"runs": 9, "balls": 17, "wickets": 1}, "3abe1ef6": {"runs": 1, "balls": 4, "wickets": 0}, "26f12506": {"runs": 3, "balls": 7, "wickets": 0}, "b0946605": {"runs": 37, "balls": 50, "wickets": 2}, "1ac2a995": {"runs": 2, "balls": 3, "wickets": 1}, "75224f22": {"runs": 7, "balls": 2, "wickets": 0}, "a757b0d8": {"runs": 12, "balls": 14, "wickets": 0}, "1be67d37": {"runs": 7, "balls": 10, "wickets": 0}, "4751caa3": {"runs": 9, "balls": 10, "wickets": 1}, "18fac429": {"runs": 11, "balls": 13, "wickets": 1}, "f0f628c7": {"runs": 1, "balls": 2, "wickets": 0}, "5531248e": {"runs": 22, "balls": 7, "wickets": 0}, "770494eb": {"runs": 12, "balls": 9, "wickets": 0}, "c0c411cb": {"runs": 5, "balls": 3, "wickets": 1}, "f78e7113": {"runs": 4, "balls": 4, "wickets": 0}, "08548b13": {"runs": 16, "balls": 17, "wickets": 0}, "2af838ee": {"runs": 39, "balls": 27, "wickets": 3}, "5b16a806": {"runs": 5, "balls": 2, "wickets": 0}, "8d5d991e": {"runs": 1, "balls": 2, "wickets": 0}, "ef6aea67": {"runs": 1, "balls": 2, "wickets": 1}, "79aad751": {"runs": 25, "balls": 10, "wickets": 0}, "c05f9d20": {"runs": 5, "balls": 5, "wickets": 0}, "0a2184d9": {"runs": 3, "balls": 3, "wickets": 1}, "73c18486": {"runs": 9, "balls": 23, "wickets": 0}, "c4d9634c": {"runs": 34, "balls": 78, "wickets": 0}, "c3b93a03": {"runs": 1, "balls": 6, "wickets": 0}, "cb5100f1": {"runs": 52, "balls": 64, "wickets": 0}, "ef18b66e": {"runs": 57, "balls": 81, "wickets": 2}, "1bb0993e": {"runs": 20, "balls": 25, "wickets": 0}, "bb95564b": {"runs": 11, "balls": 11, "wickets": 0}, "bb34fd31": {"runs": 82, "balls": 90, "wickets": 0}, "50c6bc2b": {"runs": 3, "balls": 4, "wickets": 0}, "7f048519": {"runs": 29, "balls": 24, "wickets": 1}, "5b8c830e": {"runs": 17, "balls": 35, "wickets": 1}, "23eeb873": {"runs": 2, "balls": 2, "wickets": 1}, "2ed569a0": {"runs": 17, "balls": 18, "wickets": 0}, "2cdce1be": {"runs": 13, "balls": 11, "wickets": 1}, "5b7ab5a9": {"runs": 9, "balls": 13, "wickets": 0}, "cdc6bdba": {"runs": 6, "balls": 3, "wickets": 0}, "e5437608": {"runs": 7, "balls": 16, "wickets": 0}, "9a2fc964": {"runs": 0, "balls": 2, "wickets": 0}, "3feda4fa": {"runs": 51, "balls": 72, "wickets": 0}, "cc23e91e": {"runs": 45, "balls": 106, "wickets": 1}, "78dfe704": {"runs": 48, "balls": 76, "wickets": 1}, "59ddd811": {"runs": 7, "balls": 5, "wickets": 0}, "9ab63e7b": {"runs": 2, "balls": 2, "wickets": 0}, "ee1b6c27": {"runs": 19, "balls": 11, "wickets": 0}, "efc04be7": {"runs": 13, "balls": 15, "wickets": 0}, "28d7f469": {"runs": 7, "balls": 6, "wickets": 0}, "fb3e0d39": {"runs": 17, "balls": 12, "wickets": 0}, "b3118300": {"runs": 2, "balls": 4, "wickets": 0}, "a97c8ec2": {"runs": 10, "balls": 18, "wickets": 2}, "4eb02f2e": {"runs": 13, "balls": 10, "wickets": 1}, "6ba6ca1f": {"runs": 21, "balls": 11, "wickets": 0}, "f24c6701": {"runs": 14, "balls": 8, "wickets": 0}, "ded9ff1e": {"runs": 0, "balls": 1, "wickets": 1}, "b215a7be": {"runs": 11, "balls": 9, "wickets": 0}, "732c038e": {"runs": 5, "balls": 4, "wickets": 0}, "101dcc31": {"runs": 1, "balls": 1, "wickets": 0}, "3f5f39cd": {"runs": 9, "balls": 3, "wickets": 0}, "4b6f6b73": {"runs": 5, "balls": 3, "wickets": 0}, "7ca5e05d": {"runs": 2, "balls": 2, "wickets": 0}, "81049310": {"runs": 1, "balls": 3, "wickets": 0}, "5dbdecf1": {"runs": 72, "balls": 107, "wickets": 0}, "1670dcfd": {"runs": 9, "balls": 4, "wickets": 0}, "a2421394": {"runs": 9, "balls": 12, "wickets": 2}, "d9273ee7": {"runs": 15, "balls": 13, "wickets": 0}, "86b4bf88": {"runs": 21, "balls": 22, "wickets": 1}, "7b953689": {"runs": 24, "balls": 23, "wickets": 0}, "fa433be6": {"runs": 30, "balls": 24, "wickets": 0}, "eaa76d3c": {"runs": 7, "balls": 7, "wickets": 0}, "12b610c2": {"runs": 0, "balls": 2, "wickets": 0}, "2911de16": {"runs": 7, "balls": 21, "wickets": 0}, "3086f7a4": {"runs": 37, "balls": 56, "wickets": 1}, "54c58a5e": {"runs": 119, "balls": 199, "wickets": 1}, "89c16049": {"runs": 37, "balls": 55, "wickets": 0}, "8a75e999": {"runs": 5, "balls": 4, "wickets": 0}, "24bb1c2f": {"runs": 18, "balls": 18, "wickets": 1}, "8596fe80": {"runs": 52, "balls": 29, "wickets": 1}, "9de62878": {"runs": 13, "balls": 19, "wickets": 0}, "29e253dd": {"runs": 3, "balls": 4, "wickets": 1}, "aa8d28ae": {"runs": 3, "balls": 3, "wickets": 0}, "e85d03d6": {"runs": 5, "balls": 3, "wickets": 0}, "bb134e5c": {"runs": 3, "balls": 3, "wickets": 0}, "3c87f0c3": {"runs": 1, "balls": 2, "wickets": 1}, "099135ad": {"runs": 14, "balls": 8, "wickets": 0}, "84dc72db": {"runs": 4, "balls": 5, "wickets": 0}, "b91f2a31": {"runs": 2, "balls": 2, "wickets": 0}, "f0e293b0": {"runs": 10, "balls": 11, "wickets": 1}, "adbf0400": {"runs": 12, "balls": 4, "wickets": 0}, "4557dc54": {"runs": 20, "balls": 10, "wickets": 0}, "9061a703": {"runs": 14, "balls": 9, "wickets": 0}, "fc55ec67": {"runs": 27, "balls": 20, "wickets": 0}, "3766056b": {"runs": 19, "balls": 10, "wickets": 0}, "33b3d2df": {"runs": 10, "balls": 16, "wickets": 1}, "478a63e7": {"runs": 13, "balls": 13, "wickets": 0}, "c9945bdf": {"runs": 2, "balls": 3, "wickets": 0}, "b52ffbbd": {"runs": 5, "balls": 8, "wickets": 0}, "ac5ae4af": {"runs": 46, "balls": 27, "wickets": 2}, "58431ca0": {"runs": 11, "balls": 5, "wickets": 0}, "c38d3503": {"runs": 9, "balls": 8, "wickets": 1}, "2e171977": {"runs": 48, "balls": 41, "wickets": 2}, "244048f6": {"runs": 5, "balls": 2, "wickets": 0}, "81c08fa3": {"runs": 14, "balls": 7, "wickets": 0}, "70d57519": {"runs": 36, "balls": 51, "wickets": 1}, "e9c7f0d0": {"runs": 18, "balls": 9, "wickets": 0}, "87e562a9": {"runs": 18, "balls": 8, "wickets": 0}, "57590dbb": {"runs": 3, "balls": 5, "wickets": 1}, "098a757c": {"runs": 4, "balls": 6, "wickets": 0}, "62af8546": {"runs": 6, "balls": 4, "wickets": 0}, "fdc1ac0f": {"runs": 2, "balls": 4, "wickets": 1}, "c042b412": {"runs": 1, "balls": 1, "wickets": 0}, "78adc879": {"runs": 8, "balls": 11, "wickets": 0}, "48ad3373": {"runs": 59, "balls": 95, "wickets": 0}, "e38bce7a": {"runs": 36, "balls": 54, "wickets": 2}, "2e9fdf9b": {"runs": 17, "balls": 29, "wickets": 0}, "eade4650": {"runs": 6, "balls": 11, "wickets": 1}, "5426de63": {"runs": 7, "balls": 6, "wickets": 0}, "79f5bc26": {"runs": 25, "balls": 15, "wickets": 1}, "9219eff0": {"runs": 15, "balls": 6, "wickets": 1}, "350bb1b1": {"runs": 8, "balls": 5, "wickets": 0}, "ba5e1069": {"runs": 2, "balls": 3, "wickets": 1}, "e957b38f": {"runs": 7, "balls": 11, "wickets": 0}, "1a448be0": {"runs": 5, "balls": 7, "wickets": 0}, "f5715b48": {"runs": 3, "balls": 3, "wickets": 0}, "d1988788": {"runs": 2, "balls": 2, "wickets": 0}, "28131839": {"runs": 5, "balls": 10, "wickets": 0}, "469ccead": {"runs": 2, "balls": 6, "wickets": 0}, "f42064d5": {"runs": 9, "balls": 4, "wickets": 1}, "e9a870ed": {"runs": 1, "balls": 1, "wickets": 0}, "ff1ec94d": {"runs": 7, "balls": 17, "wickets": 1}, "782fb776": {"runs": 20, "balls": 26, "wickets": 0}, "fc4375ef": {"runs": 21, "balls": 29, "wickets": 0}, "803dbf1d": {"runs": 31, "balls": 29, "wickets": 1}, "5d38476c": {"runs": 25, "balls": 31, "wickets": 0}, "7595b47f": {"runs": 16, "balls": 9, "wickets": 0}, "527c2dab": {"runs": 2, "balls": 3, "wickets": 0}, "abb7c76c": {"runs": 87, "balls": 143, "wickets": 1}, "8012d0b8": {"runs": 6, "balls": 8, "wickets": 0}, "e30c9b2d": {"runs": 5, "balls": 2, "wickets": 0}, "3ff033bb": {"runs": 8, "balls": 5, "wickets": 1}, "7d92277a": {"runs": 3, "balls": 7, "wickets": 0}, "327b58d3": {"runs": 18, "balls": 6, "wickets": 0}, "64839cb3": {"runs": 12, "balls": 6, "wickets": 0}, "736123bb": {"runs": 7, "balls": 8, "wickets": 0}, "6e3f5a5c": {"runs": 5, "balls": 2, "wickets": 0}, "aceb7654": {"runs": 6, "balls": 5, "wickets": 1}, "b40ee8a8": {"runs": 9, "balls": 12, "wickets": 0}, "9dad0f2e": {"runs": 2, "balls": 5, "wickets": 0}, "80ad39ac": {"runs": 21, "balls": 30, "wickets": 2}, "37654b75": {"runs": 2, "balls": 4, "wickets": 0}, "28392e11": {"runs": 1, "balls": 1, "wickets": 0}, "2f49c897": {"runs": 4, "balls": 2, "wickets": 1}, "3204c99f": {"runs": 5, "balls": 8, "wickets": 0}, "05c2ca46": {"runs": 4, "balls": 7, "wickets": 0}, "e734d090": {"runs": 6, "balls": 12, "wickets": 1}, "0b0cc297": {"runs": 6, "balls": 3, "wickets": 0}, "e4a0deae": {"runs": 31, "balls": 60, "wickets": 1}, "5318ee68": {"runs": 43, "balls": 46, "wickets": 1}, "5935d694": {"runs": 3, "balls": 5, "wickets": 0}, "8ce2080b": {"runs": 9, "balls": 8, "wickets": 1}, "894b2d25": {"runs": 17, "balls": 29, "wickets": 1}, "e36e9dd3": {"runs": 66, "balls": 93, "wickets": 1}, "4b685e2d": {"runs": 23, "balls": 30, "wickets": 0}, "1cc0a83d": {"runs": 11, "balls": 14, "wickets": 1}, "9a46c4e5": {"runs": 33, "balls": 43, "wickets": 2}, "cb9b8664": {"runs": 5, "balls": 6, "wickets": 0}}, "fifties": 35, "thirties": 39, "centuries": 11, "maidens": 83.0, "hattricks": 4, "runs": 7003.0, "wickets": 98.0, "club_ODI_previous3_runs": [], "club_ODI_previous3_wickets": [], "club_ODI_previous3_balls played": [], "club_ODI_previous3_overs": [], "club_ODI_previous3_runs gave": [], "club_ODI_lifetime_runs": 0.0, "club_ODI_lifetime_wickets": 0.0, "club_ODI_lifetime_balls played": 0.0, "club_ODI_lifetime_overs": 0.0, "club_ODI_lifetime_runs gave": 0.0, "club_Test_previous3_runs": [], "club_Test_previous3_wickets": [], "club_Test_previous3_balls played": [], "club_Test_previous3_overs": [], "club_Test_previous3_runs gave": [], "club_Test_lifetime_runs": 0.0, "club_Test_lifetime_wickets": 0.0, "club_Test_lifetime_balls played": 0.0, "club_Test_lifetime_overs": 0.0, "club_Test_lifetime_runs gave": 0.0, "club_T20_previous3_runs": [9.0, 5.0, 0.0], "club_T20_previous3_wickets": [0.0, 0.0, 0.0], "club_T20_previous3_balls played": [5.0, 8.0, 0.0], "club_T20_previous3_overs": [1.0, 3.0, 2.0], "club_T20_previous3_runs gave": [11.0, 23.0, 14.0], "club_T20_lifetime_runs": 669.0, "club_T20_lifetime_wickets": 20.0, "club_T20_lifetime_balls played": 525.0, "club_T20_lifetime_overs": 81.33333333333333, "club_T20_lifetime_runs gave": 592.0, "international_ODI_previous3_runs": [0.0, 34.0, 19.0], "international_ODI_previous3_wickets": [0.0, 0.0, 0.0], "international_ODI_previous3_balls played": [0.0, 36.0, 24.0], "international_ODI_previous3_overs": [1.0, 3.0, 2.0], "international_ODI_previous3_runs gave": [10.0, 20.0, 22.0], "international_ODI_lifetime_runs": 1710.0, "international_ODI_lifetime_wickets": 29.0, "international_ODI_lifetime_balls played": 2164.0, "international_ODI_lifetime_overs": 321.3333333333333, "international_ODI_lifetime_runs gave": 1674.0, "international_Test_previous3_runs": [69.0, 51.0, 44.0], "international_Test_previous3_wickets": [2.0, 2.0, 1.0], "international_Test_previous3_balls played": [110.0, 100.0, 80.0], "international_Test_previous3_overs": [4.0, 19.0, 7.0], "international_Test_previous3_runs gave": [18.0, 63.0, 30.0], "international_Test_lifetime_runs": 3881.0, "international_Test_lifetime_wickets": 35.0, "international_Test_lifetime_balls played": 6637.0, "international_Test_lifetime_overs": 634.8333333333333, "international_Test_lifetime_runs gave": 2129.0, "international_T20_previous3_runs": [8.0, 21.0, 34.0], "international_T20_previous3_wickets": [1.0, 1.0, 0.0], "international_T20_previous3_balls played": [12.0, 26.0, 26.0], "international_T20_previous3_overs": [1.0, 2.0, 0.0], "international_T20_previous3_runs gave": [2.0, 11.0, 0.0], "international_T20_lifetime_runs": 743.0, "international_T20_lifetime_wickets": 14.0, "international_T20_lifetime_balls played": 654.0, "international_T20_lifetime_overs": 47.49999999999999, "international_T20_lifetime_runs gave": 326.0}