{"played_against": {"2f28dc94": {"runs": 10, "balls": 58, "wickets": 1}, "8012d0b8": {"runs": 12, "balls": 44, "wickets": 0}, "b54b66b3": {"runs": 41, "balls": 90, "wickets": 0}, "4751caa3": {"runs": 17, "balls": 56, "wickets": 0}, "7d608e12": {"runs": 14, "balls": 43, "wickets": 0}, "5eef2118": {"runs": 7, "balls": 19, "wickets": 0}, "1bb0993e": {"runs": 2, "balls": 24, "wickets": 1}, "9d1d34bd": {"runs": 7, "balls": 27, "wickets": 1}, "1670dcfd": {"runs": 3, "balls": 7, "wickets": 0}, "2911de16": {"runs": 10, "balls": 59, "wickets": 2}, "45a7e761": {"runs": 22, "balls": 57, "wickets": 0}, "bd4ea627": {"runs": 2, "balls": 6, "wickets": 0}, "f09fc8fb": {"runs": 8, "balls": 33, "wickets": 0}, "bbc192a4": {"runs": 6, "balls": 12, "wickets": 0}, "54c58a5e": {"runs": 6, "balls": 5, "wickets": 1}}, "fifties": 0, "thirties": 2, "centuries": 0, "maidens": 0.0, "hattricks": 0, "club_ODI_previous3_runs": [], "club_ODI_previous3_wickets": [], "club_ODI_previous3_balls played": [], "club_ODI_previous3_overs": [], "club_ODI_previous3_runs gave": [], "club_ODI_lifetime_runs": 0.0, "club_ODI_lifetime_wickets": 0.0, "club_ODI_lifetime_balls played": 0.0, "club_ODI_lifetime_overs": 0.0, "club_ODI_lifetime_runs gave": 0.0, "club_Test_previous3_runs": [], "club_Test_previous3_wickets": [], "club_Test_previous3_balls played": [], "club_Test_previous3_overs": [], "club_Test_previous3_runs gave": [], "club_Test_lifetime_runs": 0.0, "club_Test_lifetime_wickets": 0.0, "club_Test_lifetime_balls played": 0.0, "club_Test_lifetime_overs": 0.0, "club_Test_lifetime_runs gave": 0.0, "club_T20_previous3_runs": [], "club_T20_previous3_wickets": [], "club_T20_previous3_balls played": [], "club_T20_previous3_overs": [], "club_T20_previous3_runs gave": [], "club_T20_lifetime_runs": 0.0, "club_T20_lifetime_wickets": 0.0, "club_T20_lifetime_balls played": 0.0, "club_T20_lifetime_overs": 0.0, "club_T20_lifetime_runs gave": 0.0, "international_ODI_previous3_runs": [], "international_ODI_previous3_wickets": [], "international_ODI_previous3_balls played": [], "international_ODI_previous3_overs": [], "international_ODI_previous3_runs gave": [], "international_ODI_lifetime_runs": 0.0, "international_ODI_lifetime_wickets": 0.0, "international_ODI_lifetime_balls played": 0.0, "international_ODI_lifetime_overs": 0.0, "international_ODI_lifetime_runs gave": 0.0, "international_Test_previous3_runs": [12.0, 28.0, 26.0], "international_Test_previous3_wickets": [0.0, 0.0, 0.0], "international_Test_previous3_balls played": [58.0, 60.0, 114.0], "international_Test_previous3_overs": [0.0, 0.0, 0.0], "international_Test_previous3_runs gave": [0.0, 0.0, 0.0], "international_Test_lifetime_runs": 167.0, "international_Test_lifetime_wickets": 0.0, "international_Test_lifetime_balls played": 543.0, "international_Test_lifetime_overs": 0.0, "international_Test_lifetime_runs gave": 0.0, "international_T20_previous3_runs": [], "international_T20_previous3_wickets": [], "international_T20_previous3_balls played": [], "international_T20_previous3_overs": [], "international_T20_previous3_runs gave": [], "international_T20_lifetime_runs": 0.0, "international_T20_lifetime_wickets": 0.0, "international_T20_lifetime_balls played": 0.0, "international_T20_lifetime_overs": 0.0, "international_T20_lifetime_runs gave": 0.0}