{"played_against": {"c498c510": {"runs": 4, "balls": 5, "wickets": 0}, "2fbb8902": {"runs": 6, "balls": 17, "wickets": 0}, "49f6d023": {"runs": 13, "balls": 17, "wickets": 0}, "479da8f9": {"runs": 3, "balls": 11, "wickets": 0}, "f49c401e": {"runs": 8, "balls": 17, "wickets": 0}, "a22b4f3f": {"runs": 3, "balls": 6, "wickets": 0}, "0e6a5cfa": {"runs": 14, "balls": 36, "wickets": 0}, "f4b6f6ac": {"runs": 9, "balls": 8, "wickets": 0}, "c573d173": {"runs": 8, "balls": 9, "wickets": 0}, "76963735": {"runs": 6, "balls": 6, "wickets": 0}, "0b8be981": {"runs": 16, "balls": 21, "wickets": 0}, "3ef46a49": {"runs": 19, "balls": 38, "wickets": 0}, "0ac067e8": {"runs": 7, "balls": 18, "wickets": 0}, "c17dcc29": {"runs": 4, "balls": 8, "wickets": 1}, "ff1e08eb": {"runs": 3, "balls": 7, "wickets": 0}, "5c93efb1": {"runs": 2, "balls": 3, "wickets": 0}, "880133fb": {"runs": 2, "balls": 4, "wickets": 1}, "7f74b21d": {"runs": 5, "balls": 11, "wickets": 1}, "609d6c7c": {"runs": 5, "balls": 14, "wickets": 0}, "c471750e": {"runs": 11, "balls": 6, "wickets": 0}, "c51c4c22": {"runs": 3, "balls": 8, "wickets": 0}, "e2abcf16": {"runs": 2, "balls": 3, "wickets": 0}, "8f929af6": {"runs": 1, "balls": 7, "wickets": 0}, "138e30ab": {"runs": 7, "balls": 2, "wickets": 0}, "027662be": {"runs": 2, "balls": 2, "wickets": 0}, "125853c3": {"runs": 3, "balls": 3, "wickets": 1}}, "fifties": 1, "thirties": 1, "centuries": 0, "maidens": 0.0, "hattricks": 0, "runs": 166.0, "wickets": 0.0, "club_ODI_previous3_runs": [], "club_ODI_previous3_wickets": [], "club_ODI_previous3_balls played": [], "club_ODI_previous3_overs": [], "club_ODI_previous3_runs gave": [], "club_ODI_lifetime_runs": 0.0, "club_ODI_lifetime_wickets": 0.0, "club_ODI_lifetime_balls played": 0.0, "club_ODI_lifetime_overs": 0.0, "club_ODI_lifetime_runs gave": 0.0, "club_Test_previous3_runs": [], "club_Test_previous3_wickets": [], "club_Test_previous3_balls played": [], "club_Test_previous3_overs": [], "club_Test_previous3_runs gave": [], "club_Test_lifetime_runs": 0.0, "club_Test_lifetime_wickets": 0.0, "club_Test_lifetime_balls played": 0.0, "club_Test_lifetime_overs": 0.0, "club_Test_lifetime_runs gave": 0.0, "club_T20_previous3_runs": [], "club_T20_previous3_wickets": [], "club_T20_previous3_balls played": [], "club_T20_previous3_overs": [], "club_T20_previous3_runs gave": [], "club_T20_lifetime_runs": 0.0, "club_T20_lifetime_wickets": 0.0, "club_T20_lifetime_balls played": 0.0, "club_T20_lifetime_overs": 0.0, "club_T20_lifetime_runs gave": 0.0, "international_ODI_previous3_runs": [37.0, 71.0, 4.0], "international_ODI_previous3_wickets": [0.0, 0.0, 0.0], "international_ODI_previous3_balls played": [73.0, 128.0, 8.0], "international_ODI_previous3_overs": [0.0, 0.0, 0.0], "international_ODI_previous3_runs gave": [0.0, 0.0, 0.0], "international_ODI_lifetime_runs": 112.0, "international_ODI_lifetime_wickets": 0.0, "international_ODI_lifetime_balls played": 209.0, "international_ODI_lifetime_overs": 0.0, "international_ODI_lifetime_runs gave": 0.0, "international_Test_previous3_runs": [], "international_Test_previous3_wickets": [], "international_Test_previous3_balls played": [], "international_Test_previous3_overs": [], "international_Test_previous3_runs gave": [], "international_Test_lifetime_runs": 0.0, "international_Test_lifetime_wickets": 0.0, "international_Test_lifetime_balls played": 0.0, "international_Test_lifetime_overs": 0.0, "international_Test_lifetime_runs gave": 0.0, "international_T20_previous3_runs": [7.0, 29.0, 18.0], "international_T20_previous3_wickets": [0.0, 0.0, 0.0], "international_T20_previous3_balls played": [14.0, 41.0, 25.0], "international_T20_previous3_overs": [0.0, 0.0, 0.0], "international_T20_previous3_runs gave": [0.0, 0.0, 0.0], "international_T20_lifetime_runs": 54.0, "international_T20_lifetime_wickets": 0.0, "international_T20_lifetime_balls played": 80.0, "international_T20_lifetime_overs": 0.0, "international_T20_lifetime_runs gave": 0.0}