{"played_against": {"81d06fb5": {"runs": 20, "balls": 54, "wickets": 1}, "f048bb41": {"runs": 37, "balls": 62, "wickets": 0}, "6c87f1df": {"runs": 3, "balls": 7, "wickets": 0}, "137e7065": {"runs": 8, "balls": 22, "wickets": 0}, "616a8149": {"runs": 24, "balls": 40, "wickets": 0}, "1b04e02b": {"runs": 21, "balls": 20, "wickets": 0}, "56b93d46": {"runs": 34, "balls": 52, "wickets": 0}, "afa7e784": {"runs": 9, "balls": 10, "wickets": 0}, "bc773eeb": {"runs": 47, "balls": 56, "wickets": 0}, "770ae773": {"runs": 41, "balls": 63, "wickets": 0}, "64775749": {"runs": 33, "balls": 45, "wickets": 3}, "56ab442f": {"runs": 17, "balls": 11, "wickets": 0}, "4933f499": {"runs": 13, "balls": 10, "wickets": 2}, "45f56920": {"runs": 13, "balls": 13, "wickets": 0}, "e7dd5eca": {"runs": 36, "balls": 47, "wickets": 1}, "14f96089": {"runs": 5, "balls": 5, "wickets": 0}, "f0e722e0": {"runs": 1, "balls": 6, "wickets": 1}, "62af8546": {"runs": 4, "balls": 3, "wickets": 0}, "7f048519": {"runs": 6, "balls": 2, "wickets": 0}, "68e26ec9": {"runs": 10, "balls": 27, "wickets": 2}, "7c7d63a2": {"runs": 15, "balls": 11, "wickets": 0}, "2318ba22": {"runs": 1, "balls": 1, "wickets": 0}, "dfc4d8b5": {"runs": 16, "balls": 12, "wickets": 0}, "e412cb64": {"runs": 1, "balls": 3, "wickets": 0}, "f1c61793": {"runs": 33, "balls": 50, "wickets": 0}, "2a2e6343": {"runs": 1, "balls": 3, "wickets": 1}, "51a60c16": {"runs": 9, "balls": 14, "wickets": 1}, "88209c84": {"runs": 12, "balls": 12, "wickets": 1}, "898e628d": {"runs": 29, "balls": 50, "wickets": 0}, "6834d1f2": {"runs": 4, "balls": 18, "wickets": 1}, "0164b064": {"runs": 78, "balls": 94, "wickets": 4}, "da13a0fc": {"runs": 19, "balls": 13, "wickets": 0}, "903560ed": {"runs": 62, "balls": 108, "wickets": 3}, "fa433be6": {"runs": 10, "balls": 21, "wickets": 1}, "479f9b04": {"runs": 6, "balls": 20, "wickets": 0}, "c89e4c9f": {"runs": 4, "balls": 3, "wickets": 0}, "96824e68": {"runs": 4, "balls": 8, "wickets": 0}, "4ba2c04d": {"runs": 2, "balls": 3, "wickets": 0}, "caf69bf7": {"runs": 6, "balls": 3, "wickets": 0}, "fb66ce1f": {"runs": 0, "balls": 2, "wickets": 1}, "5f547c8b": {"runs": 0, "balls": 3, "wickets": 1}, "15de1f5d": {"runs": 66, "balls": 78, "wickets": 0}, "9eb1455b": {"runs": 12, "balls": 18, "wickets": 1}, "72075ec1": {"runs": 6, "balls": 23, "wickets": 0}, "808f425a": {"runs": 8, "balls": 11, "wickets": 0}, "7c503806": {"runs": 5, "balls": 3, "wickets": 0}, "1a156c88": {"runs": 7, "balls": 6, "wickets": 0}, "d167edd3": {"runs": 76, "balls": 156, "wickets": 4}, "6f95e5fa": {"runs": 9, "balls": 10, "wickets": 1}, "bd93fea4": {"runs": 15, "balls": 23, "wickets": 0}, "208f22ea": {"runs": 12, "balls": 10, "wickets": 1}, "f3abd0c9": {"runs": 7, "balls": 6, "wickets": 0}, "bc2d4f2e": {"runs": 76, "balls": 111, "wickets": 1}, "9cb8d7a6": {"runs": 7, "balls": 6, "wickets": 0}, "3b53243a": {"runs": 37, "balls": 56, "wickets": 0}, "7d92277a": {"runs": 7, "balls": 8, "wickets": 1}, "1ee08e9a": {"runs": 7, "balls": 9, "wickets": 0}, "22ae3041": {"runs": 11, "balls": 13, "wickets": 2}, "d405c0d5": {"runs": 6, "balls": 14, "wickets": 0}, "3d8feaf8": {"runs": 8, "balls": 6, "wickets": 0}, "86b4bf88": {"runs": 90, "balls": 193, "wickets": 1}, "003d49e6": {"runs": 9, "balls": 9, "wickets": 0}, "442461fa": {"runs": 52, "balls": 119, "wickets": 1}, "70c4f525": {"runs": 8, "balls": 30, "wickets": 1}, "02ba80a0": {"runs": 1, "balls": 1, "wickets": 0}, "a90e53ec": {"runs": 10, "balls": 19, "wickets": 0}, "f752db61": {"runs": 6, "balls": 27, "wickets": 1}, "e5ee7c83": {"runs": 5, "balls": 6, "wickets": 2}, "b08e58e2": {"runs": 5, "balls": 21, "wickets": 0}, "245c97cb": {"runs": 0, "balls": 1, "wickets": 1}, "a2421394": {"runs": 2, "balls": 3, "wickets": 0}, "ff1e12a0": {"runs": 1, "balls": 2, "wickets": 0}, "786b7fe8": {"runs": 7, "balls": 10, "wickets": 0}, "44afbf2d": {"runs": 10, "balls": 5, "wickets": 0}, "8596fe80": {"runs": 2, "balls": 4, "wickets": 0}, "1558d83b": {"runs": 10, "balls": 15, "wickets": 1}, "218d4d78": {"runs": 6, "balls": 14, "wickets": 0}, "272fc5ad": {"runs": 19, "balls": 26, "wickets": 1}, "055be93a": {"runs": 3, "balls": 6, "wickets": 0}, "a0f612b6": {"runs": 10, "balls": 27, "wickets": 2}, "aa3c7a7a": {"runs": 33, "balls": 57, "wickets": 1}, "e94d2d50": {"runs": 21, "balls": 34, "wickets": 0}, "10735e1d": {"runs": 19, "balls": 37, "wickets": 1}, "0ebb3444": {"runs": 30, "balls": 26, "wickets": 0}, "38c276e1": {"runs": 46, "balls": 89, "wickets": 5}, "7c8f533d": {"runs": 9, "balls": 50, "wickets": 1}, "b3267eaa": {"runs": 22, "balls": 27, "wickets": 0}, "39d608d4": {"runs": 28, "balls": 53, "wickets": 0}, "ab21795b": {"runs": 71, "balls": 115, "wickets": 1}, "83c3e8e3": {"runs": 34, "balls": 47, "wickets": 1}, "59559bc2": {"runs": 2, "balls": 2, "wickets": 0}, "6c79c098": {"runs": 8, "balls": 3, "wickets": 1}, "6dd8b88c": {"runs": 2, "balls": 2, "wickets": 0}, "24bb1c2f": {"runs": 12, "balls": 6, "wickets": 1}, "d9273ee7": {"runs": 1, "balls": 1, "wickets": 0}, "57590dbb": {"runs": 6, "balls": 2, "wickets": 1}, "52c952d9": {"runs": 0, "balls": 1, "wickets": 0}, "19b9f399": {"runs": 2, "balls": 4, "wickets": 0}, "ab965cad": {"runs": 20, "balls": 24, "wickets": 0}, "098229a5": {"runs": 1, "balls": 8, "wickets": 0}, "ac2e7ec0": {"runs": 30, "balls": 53, "wickets": 0}, "739e412b": {"runs": 2, "balls": 8, "wickets": 0}, "4332744d": {"runs": 8, "balls": 22, "wickets": 0}, "4d748b6a": {"runs": 23, "balls": 26, "wickets": 0}, "b03303ca": {"runs": 28, "balls": 35, "wickets": 0}, "5355168d": {"runs": 12, "balls": 12, "wickets": 0}, "2372b3ad": {"runs": 7, "balls": 11, "wickets": 0}}, "fifties": 3, "thirties": 24, "centuries": 0, "maidens": 93.0, "hattricks": 5, "club_ODI_previous3_runs": [], "club_ODI_previous3_wickets": [], "club_ODI_previous3_balls played": [], "club_ODI_previous3_overs": [], "club_ODI_previous3_runs gave": [], "club_ODI_lifetime_runs": 0.0, "club_ODI_lifetime_wickets": 0.0, "club_ODI_lifetime_balls played": 0.0, "club_ODI_lifetime_overs": 0.0, "club_ODI_lifetime_runs gave": 0.0, "club_Test_previous3_runs": [32.0, 52.0, 88.0], "club_Test_previous3_wickets": [1.0, 1.0, 1.0], "club_Test_previous3_balls played": [75.0, 73.0, 152.0], "club_Test_previous3_overs": [26.0, 26.0, 24.0], "club_Test_previous3_runs gave": [91.0, 79.0, 83.0], "club_Test_lifetime_runs": 1336.0, "club_Test_lifetime_wickets": 35.0, "club_Test_lifetime_balls played": 2458.0, "club_Test_lifetime_overs": 461.8333333333333, "club_Test_lifetime_runs gave": 1364.0, "club_T20_previous3_runs": [16.0, 16.0, 0.0], "club_T20_previous3_wickets": [2.0, 0.0, 0.0], "club_T20_previous3_balls played": [8.0, 10.0, 0.0], "club_T20_previous3_overs": [4.0, 4.0, 2.0], "club_T20_previous3_runs gave": [27.0, 27.0, 36.0], "club_T20_lifetime_runs": 473.0, "club_T20_lifetime_wickets": 11.0, "club_T20_lifetime_balls played": 424.0, "club_T20_lifetime_overs": 37.0, "club_T20_lifetime_runs gave": 329.0, "international_ODI_previous3_runs": [], "international_ODI_previous3_wickets": [], "international_ODI_previous3_balls played": [], "international_ODI_previous3_overs": [], "international_ODI_previous3_runs gave": [], "international_ODI_lifetime_runs": 0.0, "international_ODI_lifetime_wickets": 0.0, "international_ODI_lifetime_balls played": 0.0, "international_ODI_lifetime_overs": 0.0, "international_ODI_lifetime_runs gave": 0.0, "international_Test_previous3_runs": [], "international_Test_previous3_wickets": [], "international_Test_previous3_balls played": [], "international_Test_previous3_overs": [], "international_Test_previous3_runs gave": [], "international_Test_lifetime_runs": 0.0, "international_Test_lifetime_wickets": 0.0, "international_Test_lifetime_balls played": 0.0, "international_Test_lifetime_overs": 0.0, "international_Test_lifetime_runs gave": 0.0, "international_T20_previous3_runs": [], "international_T20_previous3_wickets": [], "international_T20_previous3_balls played": [], "international_T20_previous3_overs": [], "international_T20_previous3_runs gave": [], "international_T20_lifetime_runs": 0.0, "international_T20_lifetime_wickets": 0.0, "international_T20_lifetime_balls played": 0.0, "international_T20_lifetime_overs": 0.0, "international_T20_lifetime_runs gave": 0.0}