{"played_against": {"94c0131e": {"runs": 0, "balls": 2, "wickets": 1}, "995aedfe": {"runs": 2, "balls": 5, "wickets": 0}, "34e36b65": {"runs": 11, "balls": 6, "wickets": 0}, "5e7b9318": {"runs": 2, "balls": 4, "wickets": 0}, "29ee9bf9": {"runs": 10, "balls": 8, "wickets": 0}, "895faea3": {"runs": 4, "balls": 4, "wickets": 0}, "780d1997": {"runs": 20, "balls": 5, "wickets": 0}, "1676b2d6": {"runs": 3, "balls": 10, "wickets": 0}, "898b09e8": {"runs": 1, "balls": 7, "wickets": 1}, "12c3ba4d": {"runs": 1, "balls": 17, "wickets": 0}, "98d05440": {"runs": 2, "balls": 7, "wickets": 0}, "2d8aae2f": {"runs": 1, "balls": 5, "wickets": 0}}, "fifties": 0, "thirties": 1, "centuries": 0, "maidens": 0.0, "hattricks": 0, "runs": 57.0, "wickets": 0.0, "club_ODI_previous3_runs": [], "club_ODI_previous3_wickets": [], "club_ODI_previous3_balls played": [], "club_ODI_previous3_overs": [], "club_ODI_previous3_runs gave": [], "club_ODI_lifetime_runs": 0.0, "club_ODI_lifetime_wickets": 0.0, "club_ODI_lifetime_balls played": 0.0, "club_ODI_lifetime_overs": 0.0, "club_ODI_lifetime_runs gave": 0.0, "club_Test_previous3_runs": [], "club_Test_previous3_wickets": [], "club_Test_previous3_balls played": [], "club_Test_previous3_overs": [], "club_Test_previous3_runs gave": [], "club_Test_lifetime_runs": 0.0, "club_Test_lifetime_wickets": 0.0, "club_Test_lifetime_balls played": 0.0, "club_Test_lifetime_overs": 0.0, "club_Test_lifetime_runs gave": 0.0, "club_T20_previous3_runs": [], "club_T20_previous3_wickets": [], "club_T20_previous3_balls played": [], "club_T20_previous3_overs": [], "club_T20_previous3_runs gave": [], "club_T20_lifetime_runs": 0.0, "club_T20_lifetime_wickets": 0.0, "club_T20_lifetime_balls played": 0.0, "club_T20_lifetime_overs": 0.0, "club_T20_lifetime_runs gave": 0.0, "international_ODI_previous3_runs": [49.0, 4.0, 4.0], "international_ODI_previous3_wickets": [0.0, 0.0, 0.0], "international_ODI_previous3_balls played": [33.0, 17.0, 29.0], "international_ODI_previous3_overs": [0.0, 0.0, 0.0], "international_ODI_previous3_runs gave": [0.0, 0.0, 0.0], "international_ODI_lifetime_runs": 57.0, "international_ODI_lifetime_wickets": 0.0, "international_ODI_lifetime_balls played": 81.0, "international_ODI_lifetime_overs": 0.0, "international_ODI_lifetime_runs gave": 0.0, "international_Test_previous3_runs": [], "international_Test_previous3_wickets": [], "international_Test_previous3_balls played": [], "international_Test_previous3_overs": [], "international_Test_previous3_runs gave": [], "international_Test_lifetime_runs": 0.0, "international_Test_lifetime_wickets": 0.0, "international_Test_lifetime_balls played": 0.0, "international_Test_lifetime_overs": 0.0, "international_Test_lifetime_runs gave": 0.0, "international_T20_previous3_runs": [], "international_T20_previous3_wickets": [], "international_T20_previous3_balls played": [], "international_T20_previous3_overs": [], "international_T20_previous3_runs gave": [], "international_T20_lifetime_runs": 0.0, "international_T20_lifetime_wickets": 0.0, "international_T20_lifetime_balls played": 0.0, "international_T20_lifetime_overs": 0.0, "international_T20_lifetime_runs gave": 0.0}